sentry_tablestore/kvstore/tablestore.py
sentry_tablestore/nodestore/backend.py
sentry_tablestore-1.0.0a3.dist-info/LICENSE.txt
sentry_tablestore-1.0.0a3.dist-info/METADATA
sentry_tablestore-1.0.0a3.dist-info/WHEEL
sentry_tablestore-1.0.0a3.dist-info/top_level.txt
sentry_tablestore-1.0.0a3.dist-info/RECORD
