Metadata-Version: 2.1
Name: sentry-tablestore
Version: 1.0.0a3
Summary: A Sentry extension to support Alicloud Tablestore (OTS) as a node storage backend.
Home-page: https://github.com/PMExtra/sentry-tablestore
Download-URL: https://github.com/PMExtra/sentry-tablestore
Author: PM Extra <pm@jubeat.net>
Author-email: pm@jubeat.net
License: Apache-2.0
Project-URL: Bug Tracker, https://github.com/PMExtra/sentry-tablestore/issues
Project-URL: CI, https://github.com/PMExtra/sentry-tablestore/actions
Project-URL: Source Code, https://github.com/PMExtra/sentry-tablestore
Classifier: Framework :: Django
Classifier: Intended Audience :: Developers
Classifier: Intended Audience :: System Administrators
Classifier: Operating System :: OS Independent
Classifier: Programming Language :: Python :: 3
Classifier: Topic :: Software Development
License-File: LICENSE.txt
Requires-Dist: tablestore (>=5.2.1)
Requires-Dist: sentry (>=21.9.0)
